sheepy/__init__.py
sheepy/collector.py
sheepy/sheeptest.py
sheepy-0.0.7.dist-info/LICENSE
sheepy-0.0.7.dist-info/METADATA
sheepy-0.0.7.dist-info/WHEEL
sheepy-0.0.7.dist-info/top_level.txt
sheepy-0.0.7.dist-info/RECORD
