Metadata-Version: 2.1
Name: sheepy
Version: 0.0.7
Summary: 🐑An incredible and performant library for unit testing
Home-page: https://github.com/sheep-io/sheepy
Author: BrunoCiccarino
Author-email: ciccabr9@gmail.com
Classifier: Programming Language :: Python :: 3
Classifier: License :: OSI Approved :: MIT License
Classifier: Operating System :: OS Independent
Requires-Python: >=3.8
License-File: LICENSE
